astropynamic/__init__.py
astropynamic/constants.py
astropynamic/time.py
astropynamic/twobody.py
astropynamic-0.1.0.dist-info/LICENSE.txt
astropynamic-0.1.0.dist-info/METADATA
astropynamic-0.1.0.dist-info/WHEEL
astropynamic-0.1.0.dist-info/top_level.txt
astropynamic-0.1.0.dist-info/RECORD
